Metadata-Version: 2.1
Name: openlostcat
Version: 1.0.0
Summary: Open Logic-based Simple Tag-bundle Categorizer
Home-page: https://github.com/pypa/sampleproject
Author: Lukács Gábor, Molnár András
Author-email: lukacs.hod@gmail.com, molnar.andras.jozsef@gmail.com
License: GPLv2
Platform: UNKNOWN
Classifier: Programming Language :: Python :: 3
Classifier: License :: OSI Approved :: GNU General Public License v2 (GPLv2)
Classifier: Operating System :: OS Independent
Requires-Python: >=3.6
